{
	"targetTime" : 60,
	"levelSize" : 
	{
		"y" : 20,
		"y_rel" : 0,
		"x" : 26.666,
		"x_px" : 0,
		"y_px" : 0,
		"x_rel" : 0
	},
	"blocks" : 
	[
		{
			"position" : 
			{
				"y" : 19.352500000000003,
				"y_rel" : 0,
				"x" : 17.265833333333333,
				"x_px" : 0,
				"y_px" : 0,
				"x_rel" : 0
			},
			"movement" : "fixed",
			"surfaces" : 
			[
			],
			"strong" : true,
			"actions" : 
			[
			],
			"scale" : 
			{
				"y" : 1.1316666666666668,
				"y_rel" : 0,
				"x" : 8.608333333333333,
				"x_px" : 0,
				"y_px" : 0,
				"x_rel" : 0
			},
			"bounds" : 
			[
						{
					"y" : 0,
					"y_rel" : 0,
					"x" : -1,
					"x_px" : 0,
					"y_px" : 0,
					"x_rel" : 0
				},
						{
					"y" : 0,
					"y_rel" : 0,
					"x" : 1,
					"x_px" : 0,
					"y_px" : 0,
					"x_rel" : 0
				}
			],
			"insulated" : true,
			"chargePolarity" : 1
		},
		{
			"position" : 
			{
				"y" : 13.518333333333333,
				"y_rel" : 0,
				"x" : 16.980833333333333,
				"x_px" : 0,
				"y_px" : 0,
				"x_rel" : 0
			},
			"movement" : "tracked",
			"surfaces" : 
			[
			],
			"strong" : false,
			"actions" : 
			[
			],
			"scale" : 
			{
				"y" : 5.576666666666667,
				"y_rel" : 0,
				"x" : 2.981666666666667,
				"x_px" : 0,
				"y_px" : 0,
				"x_rel" : 0
			},
			"bounds" : 
			[
						{
					"y" : 3,
					"y_rel" : 0,
					"x" : 0,
					"x_px" : 0,
					"y_px" : 0,
					"x_rel" : 0
				},
						{
					"y" : -3,
					"y_rel" : 0,
					"x" : 0,
					"x_px" : 0,
					"y_px" : 0,
					"x_rel" : 0
				}
			],
			"insulated" : false,
			"chargePolarity" : 1
		},
		{
			"position" : 
			{
				"y" : 16.175833333333333,
				"y_rel" : 0,
				"x" : 7.690833333333334,
				"x_px" : 0,
				"y_px" : 0,
				"x_rel" : 0
			},
			"movement" : "fixed",
			"surfaces" : 
			[
			],
			"strong" : false,
			"actions" : 
			[
			],
			"scale" : 
			{
				"y" : 1.0283333333333335,
				"y_rel" : 0,
				"x" : 15.338333333333333,
				"x_px" : 0,
				"y_px" : 0,
				"x_rel" : 0
			},
			"bounds" : 
			[
						{
					"y" : 0,
					"y_rel" : 0,
					"x" : -1,
					"x_px" : 0,
					"y_px" : 0,
					"x_rel" : 0
				},
						{
					"y" : 0,
					"y_rel" : 0,
					"x" : 1,
					"x_px" : 0,
					"y_px" : 0,
					"x_rel" : 0
				}
			],
			"insulated" : true,
			"chargePolarity" : 0
		},
		{
			"position" : 
			{
				"y" : 19.355833333333333,
				"y_rel" : 0,
				"x" : 24.1575,
				"x_px" : 0,
				"y_px" : 0,
				"x_rel" : 0
			},
			"movement" : "fixed",
			"surfaces" : 
			[
			],
			"strong" : false,
			"actions" : 
			[
			"up,exit"
			],
			"scale" : 
			{
				"y" : 1.0316666666666667,
				"y_rel" : 0,
				"x" : 5.071666666666667,
				"x_px" : 0,
				"y_px" : 0,
				"x_rel" : 0
			},
			"bounds" : 
			[
						{
					"y" : 0,
					"y_rel" : 0,
					"x" : -1,
					"x_px" : 0,
					"y_px" : 0,
					"x_rel" : 0
				},
						{
					"y" : 0,
					"y_rel" : 0,
					"x" : 1,
					"x_px" : 0,
					"y_px" : 0,
					"x_rel" : 0
				}
			],
			"insulated" : true,
			"chargePolarity" : 0
		}
	],
	"playerPosition" : 
	{
		"y" : 13.068333333333333,
		"y_rel" : 0,
		"x" : 8.213333333333333,
		"x_px" : 0,
		"y_px" : 0,
		"x_rel" : 0
	},
	"title" : "Discharge",
	"gravity" : 
	{
		"y" : 9.8,
		"y_rel" : 0,
		"x" : 0,
		"x_px" : 0,
		"y_px" : 0,
		"x_rel" : 0
	}
}